README.md
setup.py
Multifunction/__init__.py
Multifunction/atime.py
Multifunction/file.py
Multifunction/network1.py
Multifunction/text1.py
Multifunction/thre.py
Multifunction.egg-info/PKG-INFO
Multifunction.egg-info/SOURCES.txt
Multifunction.egg-info/dependency_links.txt
Multifunction.egg-info/top_level.txt