Metadata-Version: 1.0
Name: Multifunction
Version: 0.0.5
Summary: 2021/3/29
Home-page: http://www.grmine.top/
Author: bytfr 啃竹子
Author-email: 2678509244@qq.com
License: MIT
Platform: UNKNOWN
